funkai/__init__.py
funkai/claude.py
funkai/examples.py
funkai/funk.py
funkai/manager.py
funkai/openai.py
funkai-1.0.dist-info/METADATA
funkai-1.0.dist-info/WHEEL
funkai-1.0.dist-info/top_level.txt
funkai-1.0.dist-info/RECORD
