Metadata-Version: 2.1
Name: funkai
Version: 1.0
Summary: Easily create and deploy placeholder functions powered by OpenAI for rapid prototyping, diverse linguistic tasks, and quick insights.
Home-page: https://github.com/ciaraadkins/funkai
Author: Ciara Adkins
Author-email: adkins.ciara@gmail.com.com
Requires-Dist: openai
Requires-Dist: llmonitor
Requires-Dist: anthropic
